nas_bench_graph/__init__.py
nas_bench_graph/architecture.py
nas_bench_graph/readbench.py
nas_bench_graph/runnni.py
nas_bench_graph/light/arxiv.bench
nas_bench_graph/light/citeseer.bench
nas_bench_graph/light/computers.bench
nas_bench_graph/light/cora.bench
nas_bench_graph/light/cs.bench
nas_bench_graph/light/photo.bench
nas_bench_graph/light/physics.bench
nas_bench_graph/light/proteins.bench
nas_bench_graph/light/pubmed.bench
nas_bench_graph-1.4.0.dist-info/LICENSE
nas_bench_graph-1.4.0.dist-info/METADATA
nas_bench_graph-1.4.0.dist-info/WHEEL
nas_bench_graph-1.4.0.dist-info/top_level.txt
nas_bench_graph-1.4.0.dist-info/RECORD
