Metadata-Version: 2.1
Name: nas_bench_graph
Version: 1.4.0
Summary: NAS benchmark for graph data
Author: THUMNLab/aglteam
Author-email: autogl@tsinghua.edu.cn
Maintainer: THUMNLab/aglteam
Classifier: Development Status :: 4 - Beta
Classifier: License :: OSI Approved :: Apache Software License
Classifier: Programming Language :: Python :: 3 :: Only
Classifier: Programming Language :: Python :: 3.6
Requires-Python: ~=3.6
License-File: LICENSE
